kivytransitions/__init__.py
kivytransitions/utils.py
kivytransitions/transitions/Angular.glsl
kivytransitions/transitions/Bounce.glsl
kivytransitions/transitions/BowTieHorizontal.glsl
kivytransitions/transitions/BowTieVertical.glsl
kivytransitions/transitions/Burn.glsl
kivytransitions/transitions/ButterflyWaveScrawler.glsl
kivytransitions/transitions/CannabisLeaf.glsl
kivytransitions/transitions/Circle.glsl
kivytransitions/transitions/CircleOpen.glsl
kivytransitions/transitions/ColorPhase.glsl
kivytransitions/transitions/ColourDistance.glsl
kivytransitions/transitions/CrazyParametricFun.glsl
kivytransitions/transitions/CrossHatch.glsl
kivytransitions/transitions/CrossWarp.glsl
kivytransitions/transitions/CrossZoom.glsl
kivytransitions/transitions/Cube.glsl
kivytransitions/transitions/DirectionalEasing.glsl
kivytransitions/transitions/DirectionalWarp.glsl
kivytransitions/transitions/DirectionalWipe.glsl
kivytransitions/transitions/Displacement.glsl
kivytransitions/transitions/DoomScreenTransition.glsl
kivytransitions/transitions/Doorway.glsl
kivytransitions/transitions/Dreamy.glsl
kivytransitions/transitions/DreamyZoom.glsl
kivytransitions/transitions/Fade.glsl
kivytransitions/transitions/FadeColor.glsl
kivytransitions/transitions/FadeGrayscale.glsl
kivytransitions/transitions/FilmBurn.glsl
kivytransitions/transitions/FlyEye.glsl
kivytransitions/transitions/GlitchDisplace.glsl
kivytransitions/transitions/GlitchMemories.glsl
kivytransitions/transitions/GridFlip.glsl
kivytransitions/transitions/Heart.glsl
kivytransitions/transitions/Hexagonalize.glsl
kivytransitions/transitions/Kaleidoscope.glsl
kivytransitions/transitions/LeftRight.glsl
kivytransitions/transitions/LinearBlur.glsl
kivytransitions/transitions/Luma.glsl
kivytransitions/transitions/LuminanceMelt.glsl
kivytransitions/transitions/Morph.glsl
kivytransitions/transitions/Mosaic.glsl
kivytransitions/transitions/MultiplyBlend.glsl
kivytransitions/transitions/PageCurl.glsl
kivytransitions/transitions/Perlin.glsl
kivytransitions-1.1.dist-info/LICENSE
kivytransitions-1.1.dist-info/METADATA
kivytransitions-1.1.dist-info/WHEEL
kivytransitions-1.1.dist-info/top_level.txt
kivytransitions-1.1.dist-info/RECORD
