Metadata-Version: 2.1
Name: kivytransitions
Version: 1.1
Summary: A variety of custom screen transitions for kivy
Home-page: https://github.com/shashi278/KivyShaderTransitions
Author: Shashi Ranjan
Author-email: shashiranjankv@gmail.com
License: UNKNOWN
Keywords: transitions shaders kivy-application kivy python
Platform: UNKNOWN
Classifier: Programming Language :: Python :: 3
Classifier: License :: OSI Approved :: MIT License
Classifier: Operating System :: Android
Classifier: Operating System :: Microsoft :: Windows
Classifier: Operating System :: OS Independent
Requires-Python: >=3.6
Requires-Dist: kivy
